pdbreader/__init__.py
pdbreader/_version.py
pdbreader/parser.py
pdbreader/specification.py
pdbreader-0.1.0.dist-info/LICENSE
pdbreader-0.1.0.dist-info/METADATA
pdbreader-0.1.0.dist-info/WHEEL
pdbreader-0.1.0.dist-info/top_level.txt
pdbreader-0.1.0.dist-info/RECORD
