Metadata-Version: 2.1
Name: pdbreader
Version: 0.1.0
Summary: Simple reader for pdb (Protein Data Bank) files.
Home-page: https://github.com/brisvag/pdbreader
Author: Lorenzo Gaifas
Author-email: brisvag@gmail.com
License: GPL3
Platform: UNKNOWN
Classifier: Intended Audience :: Science/Research
Classifier: Programming Language :: Python
Classifier: Topic :: Scientific/Engineering :: Bio-Informatics
Requires-Python: >=3.7
License-File: LICENSE
Requires-Dist: pandas
